src/__init__.py
src/cli_build.py
src/cli_create.py
src/cli_test.py
src/cmd.py
src/loader_md.py
src/make_html.py
src/make_xml.py
src/prepare_md.py
src/static/checker.cpp
src/static/info.ini
src/static/statement.md
src/static/tests/01
src/static/tests/01.a
contester_cm-0.14.dist-info/METADATA
contester_cm-0.14.dist-info/WHEEL
contester_cm-0.14.dist-info/entry_points.txt
contester_cm-0.14.dist-info/top_level.txt
contester_cm-0.14.dist-info/RECORD
