Metadata-Version: 2.1
Name: contester-cm
Version: 0.14
Summary: создание задач для Contester 2.4
Home-page: https://github.com/FullDungeon/python_pip
Author: FullDungeon
Author-email: ddd.dungeon@gmail.com
License: UNKNOWN
Platform: UNKNOWN
Classifier: Programming Language :: Python :: 3.5
Classifier: License :: OSI Approved :: MIT License
Classifier: Operating System :: OS Independent
Requires-Python: >=3.5
